<?xml version="1.0" encoding="UTF-8"?>
<Page id="" version="1" templateFileName="enhanced_html_caption.xml" hasVideo="true">
<style category="standard"/>
<text_item id="cdi" component_id="cdi_01" visible="false">
<value/>
<behavior id="playAudio2" target="audioi_01"/>
<behavior id="showVideo1" target="vi_01"/>
<style/>
</text_item>
<text_item id="dli" component_id="dli_01" visible="false">
<value>Narrator</value>
<style/>
</text_item>
<audio_item visible="true" id="audioi" category="" contCategory="" contID="" allowMultiple="true" allowMultiplesLimit="0" component_id="audioi_01" characterSelected="true" file=""/>
<video_item id="vi" component_id="vi_01">
<posterImage file=""/>
<dialog_timeline>0</dialog_timeline>
<resolution w="768" h="432" platform="desktop">
<video type="mp4" file="/media/video/t2_vid_0001.mp4"/>
<video type="swf" file="/media/video/t2_vid_0001.flv"/>
</resolution>
</video_item>
</Page>